langchain_github_copilot/__init__.py
langchain_github_copilot/base.py
langchain_github_copilot/chat_models.py
langchain_github_copilot-0.4.0.dist-info/LICENSE
langchain_github_copilot-0.4.0.dist-info/METADATA
langchain_github_copilot-0.4.0.dist-info/WHEEL
langchain_github_copilot-0.4.0.dist-info/RECORD
