Metadata-Version: 2.3
Name: langchain-github-copilot
Version: 0.4.0
Summary: An integration package connecting GitHub Copilot and LangChain
License: MIT
Requires-Python: >=3.9,<4.0
Classifier: License :: OSI Approved :: MIT License
Classifier: Programming Language :: Python :: 3
Classifier: Programming Language :: Python :: 3.9
Classifier: Programming Language :: Python :: 3.10
Classifier: Programming Language :: Python :: 3.11
Classifier: Programming Language :: Python :: 3.12
Classifier: Programming Language :: Python :: 3.13
Requires-Dist: langchain-core (>=0.3.15,<0.4.0)
Requires-Dist: python-dotenv (>=1.0.1,<2.0.0)
Project-URL: Repository, https://github.com/datalayer/langchain-github-copilot
Project-URL: Source Code, https://github.com/datalayer/langchain-github-copilot
